public sealed class ce
{
  public static void a(cd paramcd, Reader paramReader)
  {
	// Byte code:
	//   0: ldc '![CDATA'
	//   2: invokevirtual toCharArray : ()[C
	//   5: astore_2
	//   6: ldc '!DOCTYP'
	//   8: invokevirtual toCharArray : ()[C
	//   11: astore_3
	//   12: bipush #100
	//   14: newarray int
	//   16: astore #4
	//   18: bipush #14
	//   20: istore #5
	//   22: sipush #8192
	//   25: newarray char
	//   27: astore #6
	//   29: new java/lang/StringBuilder
	//   32: dup
	//   33: bipush #20
	//   35: invokespecial <init> : (I)V
	//   38: astore #7
	//   40: aconst_null
	//   41: astore #8
	//   43: new cc
	//   46: dup
	//   47: invokespecial <init> : ()V
	//   50: astore #9
	//   52: iconst_0
	//   53: istore #10
	//   55: sipush #1024
	//   58: newarray char
	//   60: astore #11
	//   62: iconst_0
	//   63: istore #12
	//   65: bipush #34
	//   67: istore #13
	//   69: iconst_0
	//   70: istore #14
	//   72: iconst_0
	//   73: istore #15
	//   75: iconst_0
	//   76: istore #16
	//   78: aconst_null
	//   79: astore #17
	//   81: iconst_0
	//   82: istore #18
	//   84: iload #10
	//   86: iload #15
	//   88: if_icmplt -> 1944
	//   91: aload_1
	//   92: aload #11
	//   94: invokevirtual read : ([C)I
	//   97: istore #15
	//   99: iload #15
	//   101: iconst_m1
	//   102: if_icmpeq -> 716
	//   105: iconst_0
	//   106: istore #19
	//   108: iload #19
	//   110: iconst_1
	//   111: iadd
	//   112: istore #10
	//   114: aload #11
	//   116: iload #19
	//   118: caload
	//   119: istore #19
	//   121: iload #19
	//   123: bipush #10
	//   125: if_icmpne -> 139
	//   128: iload #18
	//   130: ifeq -> 139
	//   133: iconst_0
	//   134: istore #18
	//   136: goto -> 84
	//   139: iload #18
	//   141: ifeq -> 202
	//   144: iconst_0
	//   145: istore #18
	//   147: iload #19
	//   149: istore #20
	//   151: iload #5
	//   153: ifne -> 266
	//   156: iload #20
	//   158: bipush #60
	//   160: if_icmpne -> 223
	//   163: iload #16
	//   165: iconst_1
	//   166: iadd
	//   167: istore #19
	//   169: aload #4
	//   171: iload #16
	//   173: iload #5
	//   175: iastore
	//   176: iload #12
	//   178: ifle -> 1927
	//   181: aload_0
	//   182: aload #6
	//   184: iload #12
	//   186: invokevirtual a : ([CI)V
	//   189: iconst_0
	//   190: istore #12
	//   192: iconst_5
	//   193: istore #5
	//   195: iload #19
	//   197: istore #16
	//   199: goto -> 84
	//   202: iload #19
	//   204: bipush #13
	//   206: if_icmpne -> 1937
	//   209: bipush #10
	//   211: istore #19
	//   213: iconst_1
	//   214: istore #18
	//   216: iload #19
	//   218: istore #20
	//   220: goto -> 151
	//   223: iload #20
	//   225: bipush #38
	//   227: if_icmpne -> 253
	//   230: aload #4
	//   232: iload #16
	//   234: iload #5
	//   236: iastore
	//   237: aload #7
	//   239: iconst_0
	//   240: invokevirtual setLength : (I)V
	//   243: bipush #6
	//   245: istore #5
	//   247: iinc #16, 1
	//   250: goto -> 84
	//   253: aload #6
	//   255: iload #12
	//   257: iload #20
	//   259: castore
	//   260: iinc #12, 1
	//   263: goto -> 84
	//   266: iload #5
	//   268: iconst_1
	//   269: if_icmpne -> 398
	//   272: iload #20
	//   274: iload #13
	//   276: if_icmpne -> 313
	//   279: new java/lang/String
	//   282: astore #21
	//   284: aload #21
	//   286: aload #6
	//   288: iconst_0
	//   289: iload #12
	//   291: invokespecial <init> : ([CII)V
	//   294: aload #9
	//   296: aload #17
	//   298: aload #21
	//   300: invokevirtual a : (Ljava/lang/String;Ljava/lang/String;)V
	//   303: iconst_0
	//   304: istore #12
	//   306: bipush #7
	//   308: istore #5
	//   310: goto -> 84
	//   313: iload #20
	//   315: bipush #32
	//   317: if_icmpeq -> 341
	//   320: iload #20
	//   322: bipush #13
	//   324: if_icmpeq -> 341
	//   327: iload #20
	//   329: bipush #10
	//   331: if_icmpeq -> 341
	//   334: iload #20
	//   336: bipush #9
	//   338: if_icmpne -> 355
	//   341: aload #6
	//   343: iload #12
	//   345: bipush #32
	//   347: i2c
	//   348: castore
	//   349: iinc #12, 1
	//   352: goto -> 84
	//   355: iload #20
	//   357: bipush #38
	//   359: if_icmpne -> 385
	//   362: aload #4
	//   364: iload #16
	//   366: iload #5
	//   368: iastore
	//   369: aload #7
	//   371: iconst_0
	//   372: invokevirtual setLength : (I)V
	//   375: bipush #6
	//   377: istore #5
	//   379: iinc #16, 1
	//   382: goto -> 84
	//   385: aload #6
	//   387: iload #12
	//   389: iload #20
	//   391: castore
	//   392: iinc #12, 1
	//   395: goto -> 84
	//   398: iload #5
	//   400: iconst_2
	//   401: if_icmpne -> 480
	//   404: iload #20
	//   406: invokestatic isWhitespace : (C)Z
	//   409: ifeq -> 436
	//   412: new java/lang/String
	//   415: dup
	//   416: aload #6
	//   418: iconst_0
	//   419: iload #12
	//   421: invokespecial <init> : ([CII)V
	//   424: astore #17
	//   426: iconst_0
	//   427: istore #12
	//   429: bipush #8
	//   431: istore #5
	//   433: goto -> 84
	//   436: iload #20
	//   438: bipush #61
	//   440: if_icmpne -> 467
	//   443: new java/lang/String
	//   446: dup
	//   447: aload #6
	//   449: iconst_0
	//   450: iload #12
	//   452: invokespecial <init> : ([CII)V
	//   455: astore #17
	//   457: iconst_0
	//   458: istore #12
	//   460: bipush #9
	//   462: istore #5
	//   464: goto -> 84
	//   467: aload #6
	//   469: iload #12
	//   471: iload #20
	//   473: castore
	//   474: iinc #12, 1
	//   477: goto -> 84
	//   480: iload #5
	//   482: iconst_3
	//   483: if_icmpne -> 665
	//   486: iload #20
	//   488: bipush #62
	//   490: if_icmpne -> 564
	//   493: aload #8
	//   495: astore #21
	//   497: aload #8
	//   499: ifnonnull -> 517
	//   502: new java/lang/String
	//   505: astore #21
	//   507: aload #21
	//   509: aload #6
	//   511: iconst_0
	//   512: iload #12
	//   514: invokespecial <init> : ([CII)V
	//   517: aload_0
	//   518: aload #21
	//   520: aload #9
	//   522: invokevirtual a : (Ljava/lang/String;Lcc;)V
	//   525: aconst_null
	//   526: astore #8
	//   528: aload #9
	//   530: invokevirtual a : ()V
	//   533: iload #16
	//   535: ifne -> 551
	//   538: bipush #14
	//   540: istore #5
	//   542: iconst_0
	//   543: istore #12
	//   545: iinc #14, 1
	//   548: goto -> 84
	//   551: iinc #16, -1
	//   554: aload #4
	//   556: iload #16
	//   558: iaload
	//   559: istore #5
	//   561: goto -> 542
	//   564: iload #20
	//   566: bipush #47
	//   568: if_icmpne -> 578
	//   571: bipush #11
	//   573: istore #5
	//   575: goto -> 84
	//   578: iload #20
	//   580: invokestatic isWhitespace : (C)Z
	//   583: ifeq -> 610
	//   586: new java/lang/String
	//   589: dup
	//   590: aload #6
	//   592: iconst_0
	//   593: iload #12
	//   595: invokespecial <init> : ([CII)V
	//   598: astore #8
	//   600: iconst_0
	//   601: istore #12
	//   603: bipush #7
	//   605: istore #5
	//   607: goto -> 84
	//   610: iload #20
	//   612: bipush #58
	//   614: if_icmpne -> 623
	//   617: iconst_0
	//   618: istore #12
	//   620: goto -> 84
	//   623: iload #20
	//   625: invokestatic isLetterOrDigit : (C)Z
	//   628: ifne -> 652
	//   631: iload #20
	//   633: bipush #95
	//   635: if_icmpeq -> 652
	//   638: iload #20
	//   640: bipush #45
	//   642: if_icmpeq -> 652
	//   645: iload #20
	//   647: bipush #46
	//   649: if_icmpne -> 1912
	//   652: aload #6
	//   654: iload #12
	//   656: iload #20
	//   658: castore
	//   659: iinc #12, 1
	//   662: goto -> 84
	//   665: iload #5
	//   667: iconst_4
	//   668: if_icmpne -> 743
	//   671: iload #20
	//   673: bipush #62
	//   675: if_icmpne -> 730
	//   678: iload #16
	//   680: ifne -> 717
	//   683: bipush #14
	//   685: istore #5
	//   687: new java/lang/String
	//   690: astore #8
	//   692: aload #8
	//   694: aload #6
	//   696: iconst_0
	//   697: iload #12
	//   699: invokespecial <init> : ([CII)V
	//   702: iinc #14, -1
	//   705: aload_0
	//   706: aload #8
	//   708: invokevirtual a : (Ljava/lang/String;)V
	//   711: iload #14
	//   713: ifne -> 1921
	//   716: return
	//   717: iinc #16, -1
	//   720: aload #4
	//   722: iload #16
	//   724: iaload
	//   725: istore #5
	//   727: goto -> 687
	//   730: aload #6
	//   732: iload #12
	//   734: iload #20
	//   736: castore
	//   737: iinc #12, 1
	//   740: goto -> 84
	//   743: iload #5
	//   745: bipush #7
	//   747: if_icmpne -> 839
	//   750: iload #20
	//   752: bipush #62
	//   754: if_icmpne -> 801
	//   757: iload #16
	//   759: ifne -> 788
	//   762: bipush #14
	//   764: istore #5
	//   766: aload_0
	//   767: aload #8
	//   769: aload #9
	//   771: invokevirtual a : (Ljava/lang/String;Lcc;)V
	//   774: aconst_null
	//   775: astore #8
	//   777: aload #9
	//   779: invokevirtual a : ()V
	//   782: iinc #14, 1
	//   785: goto -> 84
	//   788: iinc #16, -1
	//   791: aload #4
	//   793: iload #16
	//   795: iaload
	//   796: istore #5
	//   798: goto -> 766
	//   801: iload #20
	//   803: bipush #47
	//   805: if_icmpne -> 815
	//   808: bipush #11
	//   810: istore #5
	//   812: goto -> 84
	//   815: iload #20
	//   817: invokestatic isWhitespace : (C)Z
	//   820: ifne -> 1912
	//   823: aload #6
	//   825: iload #12
	//   827: iload #20
	//   829: castore
	//   830: iinc #12, 1
	//   833: iconst_2
	//   834: istore #5
	//   836: goto -> 84
	//   839: iload #5
	//   841: iconst_5
	//   842: if_icmpne -> 980
	//   845: iload #16
	//   847: ifne -> 877
	//   850: bipush #14
	//   852: istore #5
	//   854: iload #20
	//   856: bipush #47
	//   858: if_icmpne -> 890
	//   861: aload #4
	//   863: iload #16
	//   865: iload #5
	//   867: iastore
	//   868: iinc #16, 1
	//   871: iconst_4
	//   872: istore #5
	//   874: goto -> 84
	//   877: iinc #16, -1
	//   880: aload #4
	//   882: iload #16
	//   884: iaload
	//   885: istore #5
	//   887: goto -> 854
	//   890: iload #20
	//   892: bipush #63
	//   894: if_icmpne -> 904
	//   897: bipush #13
	//   899: istore #5
	//   901: goto -> 84
	//   904: iload #20
	//   906: bipush #33
	//   908: if_icmpne -> 946
	//   911: aload #4
	//   913: iload #16
	//   915: iload #5
	//   917: iastore
	//   918: aconst_null
	//   919: astore #8
	//   921: aload #9
	//   923: invokevirtual a : ()V
	//   926: aload #6
	//   928: iload #12
	//   930: iload #20
	//   932: castore
	//   933: iinc #12, 1
	//   936: iinc #16, 1
	//   939: bipush #16
	//   941: istore #5
	//   943: goto -> 84
	//   946: aload #4
	//   948: iload #16
	//   950: iload #5
	//   952: iastore
	//   953: aconst_null
	//   954: astore #8
	//   956: aload #9
	//   958: invokevirtual a : ()V
	//   961: aload #6
	//   963: iload #12
	//   965: iload #20
	//   967: castore
	//   968: iinc #12, 1
	//   971: iinc #16, 1
	//   974: iconst_3
	//   975: istore #5
	//   977: goto -> 84
	//   980: iload #5
	//   982: bipush #12
	//   984: if_icmpne -> 1065
	//   987: iload #20
	//   989: bipush #62
	//   991: if_icmpne -> 1052
	//   994: iload #12
	//   996: iconst_1
	//   997: if_icmple -> 1052
	//   1000: aload #6
	//   1002: iload #12
	//   1004: iconst_1
	//   1005: isub
	//   1006: caload
	//   1007: bipush #45
	//   1009: if_icmpne -> 1052
	//   1012: aload #6
	//   1014: iload #12
	//   1016: iconst_2
	//   1017: isub
	//   1018: caload
	//   1019: bipush #45
	//   1021: if_icmpne -> 1052
	//   1024: iload #16
	//   1026: ifne -> 1039
	//   1029: bipush #14
	//   1031: istore #5
	//   1033: iconst_0
	//   1034: istore #12
	//   1036: goto -> 84
	//   1039: iinc #16, -1
	//   1042: aload #4
	//   1044: iload #16
	//   1046: iaload
	//   1047: istore #5
	//   1049: goto -> 1033
	//   1052: aload #6
	//   1054: iload #12
	//   1056: iload #20
	//   1058: castore
	//   1059: iinc #12, 1
	//   1062: goto -> 84
	//   1065: iload #5
	//   1067: bipush #14
	//   1069: if_icmpne -> 1094
	//   1072: iload #20
	//   1074: bipush #60
	//   1076: if_icmpne -> 1912
	//   1079: aload #4
	//   1081: iload #16
	//   1083: iconst_0
	//   1084: iastore
	//   1085: iinc #16, 1
	//   1088: iconst_5
	//   1089: istore #5
	//   1091: goto -> 84
	//   1094: iload #5
	//   1096: bipush #13
	//   1098: if_icmpne -> 1142
	//   1101: iload #20
	//   1103: bipush #62
	//   1105: if_icmpne -> 1912
	//   1108: iload #16
	//   1110: ifne -> 1129
	//   1113: bipush #14
	//   1115: istore #5
	//   1117: iload #5
	//   1119: ifne -> 1918
	//   1122: bipush #14
	//   1124: istore #5
	//   1126: goto -> 84
	//   1129: iinc #16, -1
	//   1132: aload #4
	//   1134: iload #16
	//   1136: iaload
	//   1137: istore #5
	//   1139: goto -> 1117
	//   1142: iload #5
	//   1144: bipush #16
	//   1146: if_icmpne -> 1272
	//   1149: iload #20
	//   1151: bipush #45
	//   1153: if_icmpne -> 1193
	//   1156: iload #12
	//   1158: iconst_1
	//   1159: if_icmple -> 1193
	//   1162: aload #6
	//   1164: iload #12
	//   1166: iconst_1
	//   1167: isub
	//   1168: caload
	//   1169: bipush #45
	//   1171: if_icmpne -> 1193
	//   1174: aload #6
	//   1176: iload #12
	//   1178: iconst_2
	//   1179: isub
	//   1180: caload
	//   1181: bipush #33
	//   1183: if_icmpne -> 1193
	//   1186: bipush #12
	//   1188: istore #5
	//   1190: goto -> 84
	//   1193: iload #20
	//   1195: bipush #91
	//   1197: if_icmpne -> 1226
	//   1200: iload #12
	//   1202: bipush #7
	//   1204: if_icmpne -> 1226
	//   1207: aload_2
	//   1208: aload #6
	//   1210: invokestatic a : ([C[C)Z
	//   1213: ifeq -> 1226
	//   1216: iconst_0
	//   1217: istore #12
	//   1219: bipush #15
	//   1221: istore #5
	//   1223: goto -> 84
	//   1226: iload #20
	//   1228: bipush #69
	//   1230: if_icmpne -> 1259
	//   1233: iload #12
	//   1235: bipush #7
	//   1237: if_icmpne -> 1259
	//   1240: aload_3
	//   1241: aload #6
	//   1243: invokestatic a : ([C[C)Z
	//   1246: ifeq -> 1259
	//   1249: iconst_0
	//   1250: istore #12
	//   1252: bipush #17
	//   1254: istore #5
	//   1256: goto -> 84
	//   1259: aload #6
	//   1261: iload #12
	//   1263: iload #20
	//   1265: castore
	//   1266: iinc #12, 1
	//   1269: goto -> 84
	//   1272: iload #5
	//   1274: bipush #6
	//   1276: if_icmpne -> 1592
	//   1279: iload #20
	//   1281: bipush #59
	//   1283: if_icmpne -> 1581
	//   1286: iload #16
	//   1288: ifne -> 1332
	//   1291: bipush #14
	//   1293: istore #5
	//   1295: aload #7
	//   1297: invokevirtual toString : ()Ljava/lang/String;
	//   1300: astore #21
	//   1302: aload #7
	//   1304: iconst_0
	//   1305: invokevirtual setLength : (I)V
	//   1308: aload #21
	//   1310: ldc 'lt'
	//   1312: invokevirtual equals : (Ljava/lang/Object;)Z
	//   1315: ifeq -> 1345
	//   1318: aload #6
	//   1320: iload #12
	//   1322: bipush #60
	//   1324: i2c
	//   1325: castore
	//   1326: iinc #12, 1
	//   1329: goto -> 84
	//   1332: iinc #16, -1
	//   1335: aload #4
	//   1337: iload #16
	//   1339: iaload
	//   1340: istore #5
	//   1342: goto -> 1295
	//   1345: aload #21
	//   1347: ldc 'gt'
	//   1349: invokevirtual equals : (Ljava/lang/Object;)Z
	//   1352: ifeq -> 1369
	//   1355: aload #6
	//   1357: iload #12
	//   1359: bipush #62
	//   1361: i2c
	//   1362: castore
	//   1363: iinc #12, 1
	//   1366: goto -> 84
	//   1369: aload #21
	//   1371: ldc 'amp'
	//   1373: invokevirtual equals : (Ljava/lang/Object;)Z
	//   1376: ifeq -> 1393
	//   1379: aload #6
	//   1381: iload #12
	//   1383: bipush #38
	//   1385: i2c
	//   1386: castore
	//   1387: iinc #12, 1
	//   1390: goto -> 84
	//   1393: aload #21
	//   1395: ldc 'quot'
	//   1397: invokevirtual equals : (Ljava/lang/Object;)Z
	//   1400: ifeq -> 1417
	//   1403: aload #6
	//   1405: iload #12
	//   1407: bipush #34
	//   1409: i2c
	//   1410: castore
	//   1411: iinc #12, 1
	//   1414: goto -> 84
	//   1417: aload #21
	//   1419: ldc 'apos'
	//   1421: invokevirtual equals : (Ljava/lang/Object;)Z
	//   1424: ifeq -> 1441
	//   1427: aload #6
	//   1429: iload #12
	//   1431: bipush #39
	//   1433: i2c
	//   1434: castore
	//   1435: iinc #12, 1
	//   1438: goto -> 84
	//   1441: aload #21
	//   1443: ldc '#x'
	//   1445: invokevirtual startsWith : (Ljava/lang/String;)Z
	//   1448: ifeq -> 1475
	//   1451: aload #6
	//   1453: iload #12
	//   1455: aload #21
	//   1457: iconst_2
	//   1458: invokevirtual substring : (I)Ljava/lang/String;
	//   1461: bipush #16
	//   1463: invokestatic parseInt : (Ljava/lang/String;I)I
	//   1466: i2c
	//   1467: i2c
	//   1468: castore
	//   1469: iinc #12, 1
	//   1472: goto -> 84
	//   1475: aload #21
	//   1477: ldc '#'
	//   1479: invokevirtual startsWith : (Ljava/lang/String;)Z
	//   1482: ifeq -> 1507
	//   1485: aload #6
	//   1487: iload #12
	//   1489: aload #21
	//   1491: iconst_1
	//   1492: invokevirtual substring : (I)Ljava/lang/String;
	//   1495: invokestatic parseInt : (Ljava/lang/String;)I
	//   1498: i2c
	//   1499: i2c
	//   1500: castore
	//   1501: iinc #12, 1
	//   1504: goto -> 84
	//   1507: iload #12
	//   1509: iconst_1
	//   1510: iadd
	//   1511: istore #19
	//   1513: aload #6
	//   1515: iload #12
	//   1517: bipush #38
	//   1519: i2c
	//   1520: castore
	//   1521: aload #21
	//   1523: invokevirtual length : ()I
	//   1526: istore #22
	//   1528: iconst_0
	//   1529: istore #23
	//   1531: iload #19
	//   1533: istore #12
	//   1535: iload #23
	//   1537: istore #19
	//   1539: iload #19
	//   1541: iload #22
	//   1543: if_icmpge -> 1567
	//   1546: aload #6
	//   1548: iload #12
	//   1550: aload #21
	//   1552: iload #19
	//   1554: invokevirtual charAt : (I)C
	//   1557: castore
	//   1558: iinc #19, 1
	//   1561: iinc #12, 1
	//   1564: goto -> 1539
	//   1567: aload #6
	//   1569: iload #12
	//   1571: bipush #59
	//   1573: i2c
	//   1574: castore
	//   1575: iinc #12, 1
	//   1578: goto -> 84
	//   1581: aload #7
	//   1583: iload #20
	//   1585: invokevirtual append : (C)Ljava/lang/StringBuilder;
	//   1588: pop
	//   1589: goto -> 84
	//   1592: iload #5
	//   1594: bipush #15
	//   1596: if_icmpne -> 1687
	//   1599: iload #20
	//   1601: bipush #62
	//   1603: if_icmpne -> 1674
	//   1606: iload #12
	//   1608: iconst_1
	//   1609: if_icmple -> 1674
	//   1612: aload #6
	//   1614: iload #12
	//   1616: iconst_1
	//   1617: isub
	//   1618: caload
	//   1619: bipush #93
	//   1621: if_icmpne -> 1674
	//   1624: aload #6
	//   1626: iload #12
	//   1628: iconst_2
	//   1629: isub
	//   1630: caload
	//   1631: bipush #93
	//   1633: if_icmpne -> 1674
	//   1636: aload_0
	//   1637: aload #6
	//   1639: iload #12
	//   1641: iconst_2
	//   1642: isub
	//   1643: invokevirtual a : ([CI)V
	//   1646: iload #16
	//   1648: ifne -> 1661
	//   1651: bipush #14
	//   1653: istore #5
	//   1655: iconst_0
	//   1656: istore #12
	//   1658: goto -> 84
	//   1661: iinc #16, -1
	//   1664: aload #4
	//   1666: iload #16
	//   1668: iaload
	//   1669: istore #5
	//   1671: goto -> 1655
	//   1674: aload #6
	//   1676: iload #12
	//   1678: iload #20
	//   1680: castore
	//   1681: iinc #12, 1
	//   1684: goto -> 84
	//   1687: iload #5
	//   1689: bipush #11
	//   1691: if_icmpne -> 1769
	//   1694: aload #8
	//   1696: ifnonnull -> 1915
	//   1699: new java/lang/String
	//   1702: astore #8
	//   1704: aload #8
	//   1706: aload #6
	//   1708: iconst_0
	//   1709: iload #12
	//   1711: invokespecial <init> : ([CII)V
	//   1714: aload_0
	//   1715: aload #8
	//   1717: aload #9
	//   1719: invokevirtual a : (Ljava/lang/String;Lcc;)V
	//   1722: aload_0
	//   1723: aload #8
	//   1725: invokevirtual a : (Ljava/lang/String;)V
	//   1728: iload #14
	//   1730: ifeq -> 716
	//   1733: aload #9
	//   1735: invokevirtual a : ()V
	//   1738: aconst_null
	//   1739: astore #8
	//   1741: iload #16
	//   1743: ifne -> 1756
	//   1746: bipush #14
	//   1748: istore #5
	//   1750: iconst_0
	//   1751: istore #12
	//   1753: goto -> 84
	//   1756: iinc #16, -1
	//   1759: aload #4
	//   1761: iload #16
	//   1763: iaload
	//   1764: istore #5
	//   1766: goto -> 1750
	//   1769: iload #5
	//   1771: bipush #9
	//   1773: if_icmpne -> 1800
	//   1776: iload #20
	//   1778: bipush #34
	//   1780: if_icmpeq -> 1790
	//   1783: iload #20
	//   1785: bipush #39
	//   1787: if_icmpne -> 1912
	//   1790: iload #20
	//   1792: istore #13
	//   1794: iconst_1
	//   1795: istore #5
	//   1797: goto -> 84
	//   1800: iload #5
	//   1802: bipush #8
	//   1804: if_icmpne -> 1821
	//   1807: iload #20
	//   1809: bipush #61
	//   1811: if_icmpne -> 1912
	//   1814: bipush #9
	//   1816: istore #5
	//   1818: goto -> 84
	//   1821: iload #5
	//   1823: bipush #17
	//   1825: if_icmpne -> 1912
	//   1828: iload #20
	//   1830: bipush #62
	//   1832: if_icmpne -> 1889
	//   1835: iload #12
	//   1837: ifle -> 1889
	//   1840: aload #6
	//   1842: iload #12
	//   1844: iconst_1
	//   1845: isub
	//   1846: caload
	//   1847: bipush #93
	//   1849: if_icmpne -> 1889
	//   1852: iload #16
	//   1854: ifne -> 1876
	//   1857: bipush #14
	//   1859: istore #5
	//   1861: iload #5
	//   1863: ifne -> 1906
	//   1866: iconst_0
	//   1867: istore #12
	//   1869: bipush #14
	//   1871: istore #5
	//   1873: goto -> 84
	//   1876: iinc #16, -1
	//   1879: aload #4
	//   1881: iload #16
	//   1883: iaload
	//   1884: istore #5
	//   1886: goto -> 1861
	//   1889: aload #6
	//   1891: iload #12
	//   1893: iload #20
	//   1895: castore
	//   1896: iinc #12, 1
	//   1899: goto -> 84
	//   1902: astore_0
	//   1903: goto -> 716
	//   1906: iconst_0
	//   1907: istore #12
	//   1909: goto -> 84
	//   1912: goto -> 84
	//   1915: goto -> 1714
	//   1918: goto -> 84
	//   1921: iconst_0
	//   1922: istore #12
	//   1924: goto -> 84
	//   1927: iconst_5
	//   1928: istore #5
	//   1930: iload #19
	//   1932: istore #16
	//   1934: goto -> 84
	//   1937: iload #19
	//   1939: istore #20
	//   1941: goto -> 151
	//   1944: iload #10
	//   1946: istore #19
	//   1948: goto -> 108
	// Exception table:
	//   from	to	target	type
	//   91	99	1902	java/io/IOException
	//   181	189	1902	java/io/IOException
	//   237	243	1902	java/io/IOException
	//   279	303	1902	java/io/IOException
	//   369	375	1902	java/io/IOException
	//   404	426	1902	java/io/IOException
	//   443	457	1902	java/io/IOException
	//   502	517	1902	java/io/IOException
	//   517	525	1902	java/io/IOException
	//   528	533	1902	java/io/IOException
	//   578	600	1902	java/io/IOException
	//   623	631	1902	java/io/IOException
	//   687	702	1902	java/io/IOException
	//   705	711	1902	java/io/IOException
	//   766	774	1902	java/io/IOException
	//   777	782	1902	java/io/IOException
	//   815	823	1902	java/io/IOException
	//   921	926	1902	java/io/IOException
	//   956	961	1902	java/io/IOException
	//   1207	1216	1902	java/io/IOException
	//   1240	1249	1902	java/io/IOException
	//   1295	1318	1902	java/io/IOException
	//   1345	1355	1902	java/io/IOException
	//   1369	1379	1902	java/io/IOException
	//   1393	1403	1902	java/io/IOException
	//   1417	1427	1902	java/io/IOException
	//   1441	1469	1902	java/io/IOException
	//   1475	1501	1902	java/io/IOException
	//   1521	1528	1902	java/io/IOException
	//   1546	1558	1902	java/io/IOException
	//   1581	1589	1902	java/io/IOException
	//   1636	1646	1902	java/io/IOException
	//   1699	1714	1902	java/io/IOException
	//   1714	1728	1902	java/io/IOException
	//   1733	1738	1902	java/io/IOException
  }

  private static bool a(char[] paramArrayOfchar1, char[] paramArrayOfchar2)
  {
	// Byte code:
	//   0: aload_0
	//   1: arraylength
	//   2: iconst_1
	//   3: isub
	//   4: istore_2
	//   5: iload_2
	//   6: iflt -> 28
	//   9: aload_0
	//   10: iload_2
	//   11: caload
	//   12: aload_1
	//   13: iload_2
	//   14: caload
	//   15: if_icmpeq -> 22
	//   18: iconst_0
	//   19: istore_3
	//   20: iload_3
	//   21: ireturn
	//   22: iinc #2, -1
	//   25: goto -> 5
	//   28: iconst_1
	//   29: istore_3
	//   30: goto -> 20
  }
}


/* Location:              C:\Temp\dex\YT1-dex2jar.jar!\ce.class
 * Java compiler version: 6 (50.0)
 * JD-Core Version:       1.1.3
 */